bindery/__init__.py
bindery/core/generator.py
bindery/core/models.py
bindery/core/scanner.py
bindery-0.0.1.dist-info/METADATA
bindery-0.0.1.dist-info/WHEEL
bindery-0.0.1.dist-info/licenses/LICENSE
bindery-0.0.1.dist-info/RECORD
