Metadata-Version: 2.4
Name: bindery
Version: 0.0.1
Summary: A modern, automated C++ binding generator for Python using nanobind.
Project-URL: Documentation, https://github.com/yourusername/bindery#readme
Project-URL: Issues, https://github.com/yourusername/bindery/issues
Project-URL: Source, https://github.com/yourusername/bindery
Author-email: Connectomics Team <connectomics@google.com>
License:                     GNU AFFERO GENERAL PUBLIC LICENSE
License-File: LICENSE
Classifier: Development Status :: 2 - Pre-Alpha
Classifier: Programming Language :: Python
Classifier: Programming Language :: Python :: 3.10
Classifier: Programming Language :: Python :: 3.11
Classifier: Programming Language :: Python :: 3.12
Classifier: Programming Language :: Python :: Implementation :: CPython
Classifier: Programming Language :: Python :: Implementation :: PyPy
Requires-Python: >=3.10
Requires-Dist: fastapi>=0.100
Requires-Dist: jinja2>=3.0
Requires-Dist: libclang>=16.0
Requires-Dist: pydantic>=2.0
